pigeon/__init__.py
pigeon/pigeon.py
pigeon/core/__init__.py
pigeon/core/pipeline.py
pigeon/examples/__init__.py
pigeon/examples/default_exome_pipeline.conf
pigeon/examples/example.conf
pigeon/examples/example_config.conf
pigeon/utils/__init__.py
pigeon/utils/copyexamplefiles.py
pigeon/utils/parseconfig.py
pigeon/utils/runpipe.py
seq_pigeon-0.4.3.dist-info/LICENSE
seq_pigeon-0.4.3.dist-info/METADATA
seq_pigeon-0.4.3.dist-info/WHEEL
seq_pigeon-0.4.3.dist-info/entry_points.txt
seq_pigeon-0.4.3.dist-info/top_level.txt
seq_pigeon-0.4.3.dist-info/RECORD
