Metadata-Version: 2.1
Name: seq-pigeon
Version: 0.4.3
Summary: Pipeline tool for NGS data
Home-page: UNKNOWN
Author: bars
Author-email: barslmn@gmail.com
License: UNKNOWN
Keywords: genomics next generation sequencing pipeline variant discovery clinical genetics
Platform: UNKNOWN
Classifier: Development Status :: 3 - Alpha
Classifier: Intended Audience :: Developers
Classifier: Topic :: Software Development :: Build Tools
Classifier: License :: OSI Approved :: MIT License
Classifier: Programming Language :: Python :: 3
